demo_y1/verilog/exy.v
`timescale 1ns/10ps
module fn_sw(
	a, 
	b,
	sel,
	y
	);
input	a;
input	b;
input	sel;
output	y;

//assign	y=sel?(a^b):(a&b);

//用always语句块实现组合逻辑；
reg	y;

always@(a or b or sel) begin
	if(sel==1) begin
		y<=a^b;
	end
	else begin
		y<=a&b;
	end
end

endmodule

demo_y1/verilog/exy_tb.v
//------testbench of fn_sw-------
`include "exy.v"
module fn_sw_tb;
reg	a,b,sel;
wire	y;
fn_sw	 fn_sw(
	.a(a),
	.b(b),
	.sel(sel),
	.y(y)
	);
initial begin
		a<=0;b<=0;sel<=0;
	#10	a<=0;b<=0;sel<=1;	
	#10	a<=0;b<=1;sel<=0;
	#10	a<=0;b<=1;sel<=1;
	#10	a<=1;b<=0;sel<=0;
	#10	a<=1;b<=0;sel<=1;
	#10	a<=1;b<=1;sel<=0;
	#10	a<=1;b<=1;sel<=1;
	#10	$stop;
end

initial begin
        $dumpfile("wave2.vcd"); 
		$dumpvars; // dump all vars
end

endmodule

demo_y1/verilog/wave2.vcd
$date
	Wed Jun 23 20:17:22 2021
$end
$version
	Icarus Verilog
$end
$timescale
	10ps
$end
$scope module fn_sw_tb $end
$var wire 1 ! y $end
$var reg 1 " a $end
$var reg 1 # b $end
$var reg 1 $ sel $end
$scope module fn_sw $end
$var wire 1 " a $end
$var wire 1 # b $end
$var wire 1 $ sel $end
$var reg 1 ! y $end
$upscope $end
$upscope $end
$enddefinitions $end
#0
$dumpvars
0$
0#
0"
0!
$end
#1000
1$
#2000
0$
1#
#3000
1!
1$
#4000
0!
0$
0#
1"
#5000
1!
1$
#6000
0$
1#
#7000
0!
1$
